quick_parallel/__init__.py
quick_parallel/examples.py
quick_parallel/process.py
quick_parallel/unit_test.py
quick_parallel-0.0.1.3.dist-info/LICENSE
quick_parallel-0.0.1.3.dist-info/METADATA
quick_parallel-0.0.1.3.dist-info/WHEEL
quick_parallel-0.0.1.3.dist-info/top_level.txt
quick_parallel-0.0.1.3.dist-info/RECORD
