Metadata-Version: 2.1
Name: quick_parallel
Version: 0.0.1.3
Summary: Quick parallel processing library
Home-page: https://github.com/MAGALA-RICHARD/quick_parallel
Author: Richard Magala
Author-email: magalarich20@gmail.com
License: MIT
Keywords: python,quick parallel,worker,cores,threading,parallel processing
Classifier: Development Status :: 3 - Alpha
Classifier: Intended Audience :: Developers
Classifier: License :: OSI Approved :: MIT License
Classifier: Programming Language :: Python :: 3
Classifier: Operating System :: Microsoft :: Windows
Classifier: Operating System :: MacOS
Classifier: Operating System :: POSIX :: Linux
Requires-Python: >=3.4
License-File: LICENSE
Requires-Dist: tqdm>=4.66.2
